datacrawler_test_sdk/__init__.py
datacrawler_test_sdk/data_crawler.py
datacrawler_test_sdk/utils.py
datacrawler_test_sdk-1.0.2.dist-info/METADATA
datacrawler_test_sdk-1.0.2.dist-info/WHEEL
datacrawler_test_sdk-1.0.2.dist-info/top_level.txt
datacrawler_test_sdk-1.0.2.dist-info/RECORD
