Metadata-Version: 2.4
Name: datacrawler-test-sdk
Version: 1.0.2
Summary: A Smart, Automatic, Fast and Lightweight Web Scraper for Python
Home-page: https://github.com/siddharth-shah-17/Datacrawler-Experimental
Author: Siddharth Shah
Author-email: Siddharth Shah <team@svector.co.in>
License: MIT
Keywords: scraping,scraper,crawler,web scraping,data extraction
Classifier: Development Status :: 4 - Beta
Classifier: License :: OSI Approved :: MIT License
Classifier: Programming Language :: Python :: 3
Classifier: Programming Language :: Python :: 3.6
Classifier: Programming Language :: Python :: 3.7
Classifier: Programming Language :: Python :: 3.8
Classifier: Programming Language :: Python :: 3.9
Classifier: Programming Language :: Python :: 3.10
Classifier: Programming Language :: Python :: 3.11
Classifier: Programming Language :: Python :: 3.12
Classifier: Intended Audience :: Developers
Classifier: Topic :: Software Development :: Libraries :: Python Modules
Classifier: Topic :: Internet :: WWW/HTTP :: Dynamic Content
Requires-Python: >=3.6
Requires-Dist: requests
Requires-Dist: beautifulsoup4
Requires-Dist: lxml
Dynamic: author
Dynamic: description-content-type
Dynamic: home-page
Dynamic: requires-python
